musicvideos/__init__.py
musicvideos/audio_mod.py
musicvideos/images.py
musicvideos/video.py
musicvideos/fonts/__init__.py
musicvideos/fonts/down1.ttf
musicvideos/fonts/down2.ttf
musicvideos/fonts/toptext.ttf
musicvideos/vst/__init__.py
musicvideos/vst/TAL-Reverb-4.vst3/Contents/x86_64-linux/TAL-Reverb-4.so
musicvideos-1.1.0.dist-info/LICENSE
musicvideos-1.1.0.dist-info/METADATA
musicvideos-1.1.0.dist-info/WHEEL
musicvideos-1.1.0.dist-info/top_level.txt
musicvideos-1.1.0.dist-info/RECORD
